dattri/__init__.py
dattri/task.py
dattri/algorithm/__init__.py
dattri/algorithm/base.py
dattri/algorithm/data_shapley.py
dattri/algorithm/influence_function.py
dattri/algorithm/rps.py
dattri/algorithm/tracin.py
dattri/algorithm/trak.py
dattri/algorithm/utils.py
dattri/benchmark/__init__.py
dattri/benchmark/load.py
dattri/benchmark/utils.py
dattri/benchmark/datasets/__init__.py
dattri/benchmark/datasets/cifar/__init__.py
dattri/benchmark/datasets/cifar/cifar_resnet9.py
dattri/benchmark/datasets/cifar/data.py
dattri/benchmark/datasets/imagenet/__init__.py
dattri/benchmark/datasets/imagenet/data.py
dattri/benchmark/datasets/imagenet/imagenet_resnet18.py
dattri/benchmark/datasets/maestro/__init__.py
dattri/benchmark/datasets/maestro/data.py
dattri/benchmark/datasets/maestro/maestro_musictransformer.py
dattri/benchmark/datasets/mnist/__init__.py
dattri/benchmark/datasets/mnist/data.py
dattri/benchmark/datasets/mnist/mnist_lr.py
dattri/benchmark/datasets/mnist/mnist_mlp.py
dattri/benchmark/datasets/shakespeare_char/__init__.py
dattri/benchmark/datasets/shakespeare_char/data.py
dattri/benchmark/datasets/shakespeare_char/prepare.py
dattri/benchmark/datasets/tinystories/prepare.py
dattri/benchmark/models/__init__.py
dattri/benchmark/models/MusicTransformer/__init__.py
dattri/benchmark/models/MusicTransformer/generate.py
dattri/benchmark/models/MusicTransformer/loss.py
dattri/benchmark/models/MusicTransformer/music_transformer.py
dattri/benchmark/models/MusicTransformer/positional_encoding.py
dattri/benchmark/models/MusicTransformer/rpr.py
dattri/benchmark/models/MusicTransformer/dataset/__init__.py
dattri/benchmark/models/MusicTransformer/dataset/e_piano.py
dattri/benchmark/models/MusicTransformer/dataset/preprocess_midi.py
dattri/benchmark/models/MusicTransformer/midi_processor/__init__.py
dattri/benchmark/models/MusicTransformer/midi_processor/processor.py
dattri/benchmark/models/MusicTransformer/utilities/__init__.py
dattri-0.2.0.dist-info/LICENSE
dattri-0.2.0.dist-info/METADATA
dattri-0.2.0.dist-info/WHEEL
dattri-0.2.0.dist-info/entry_points.txt
dattri-0.2.0.dist-info/top_level.txt
dattri-0.2.0.dist-info/RECORD
