Metadata-Version: 2.1
Name: dattri
Version: 0.2.0
Summary: A library for data attribution tools and benchmarks.
Author-email: TRAIS-Lab <jiaqima.mle@gmail.com>
Project-URL: homepage, https://github.com/TRAIS-Lab/dattri
Classifier: License :: OSI Approved :: Apache Software License
Classifier: Programming Language :: Python :: 3
Classifier: Programming Language :: Python :: 3.10
Classifier: Programming Language :: Python :: Implementation :: CPython
Requires-Python: >=3.8
License-File: LICENSE
Requires-Dist: numpy>=1.25
Requires-Dist: scipy>=1.11
Requires-Dist: pyyaml
Requires-Dist: pretty-midi
Provides-Extra: fast_jl
Requires-Dist: fast-jl; extra == "fast-jl"
Provides-Extra: test
Requires-Dist: build; extra == "test"
Requires-Dist: pytest; extra == "test"
Requires-Dist: pre-commit; extra == "test"
Requires-Dist: ruff; extra == "test"
Requires-Dist: darglint; extra == "test"
Requires-Dist: scikit-learn; extra == "test"
Requires-Dist: pretty-midi; extra == "test"
Requires-Dist: requests; extra == "test"
